deltabase/__init__.py
deltabase/magic.py
deltabase-1.1.0.dist-info/LICENSE
deltabase-1.1.0.dist-info/METADATA
deltabase-1.1.0.dist-info/WHEEL
deltabase-1.1.0.dist-info/RECORD
