Metadata-Version: 2.1
Name: deltabase
Version: 1.1.0
Summary: 
Author: uname-n
Author-email: git@defend.sh
Requires-Python: >=3.11,<4.0
Classifier: Programming Language :: Python :: 3
Classifier: Programming Language :: Python :: 3.11
Classifier: Programming Language :: Python :: 3.12
Classifier: Programming Language :: Python :: 3.13
Provides-Extra: ai
Provides-Extra: magic
Requires-Dist: deltalake (>=0.19.0,<0.20.0)
Requires-Dist: ipython (>=8.26.0,<9.0.0) ; extra == "magic" or extra == "ai"
Requires-Dist: openai (>=1.43.0,<2.0.0) ; extra == "ai"
Requires-Dist: polars (>=1.6.0,<2.0.0)
